README
setup.py
celestron_point.egg-info/PKG-INFO
celestron_point.egg-info/SOURCES.txt
celestron_point.egg-info/dependency_links.txt
celestron_point.egg-info/requires.txt
celestron_point.egg-info/top_level.txt
point/__init__.py
point/nexstar.py