Metadata-Version: 1.1
Name: celestron-point
Version: 0.0.2
Summary: Control Celestron telescopes from Python
Home-page: https://github.com/minichate/point
Author: Christopher Troup
Author-email: minichate@gmail.com
License: BSD
Keywords: celestron,nexstar,telescope
Platform: UNKNOWN
Classifier: Development Status :: 3 - Alpha
Classifier: Topic :: Utilities
Classifier: License :: OSI Approved :: BSD License
